nojazz/__init__.py
nojazz/pandas.py
nojazz/sqlite.py
nojazz-0.0.3.dist-info/METADATA
nojazz-0.0.3.dist-info/WHEEL
nojazz-0.0.3.dist-info/top_level.txt
nojazz-0.0.3.dist-info/RECORD
